quagnes/__init__.py
quagnes/agnes.py
quagnes-1.1.0.dist-info/LICENSE.txt
quagnes-1.1.0.dist-info/METADATA
quagnes-1.1.0.dist-info/WHEEL
quagnes-1.1.0.dist-info/top_level.txt
quagnes-1.1.0.dist-info/RECORD
