Metadata-Version: 2.1
Name: quagnes
Version: 1.1.0
Summary: This package solves Agnes (Agnes Sorel) solitaire card games. It can be used to solve games having the rules implemented in the GNOME AisleRiot package and the rules attributed to Dalton in 1909 and Parlett in 1979 among others and to calculate win rates.
Author-email: Ray Griner <rgriner_fwd@outlook.com>
License: GNU GENERAL PUBLIC LICENSE
Keywords: patience,solitaire,solver,Agnes
Classifier: Programming Language :: Python :: 3
Classifier: License :: OSI Approved :: GNU General Public License v3 or later (GPLv3+)
Classifier: Operating System :: OS Independent
Classifier: Development Status :: 3 - Alpha
Classifier: Topic :: Games/Entertainment :: Simulation
License-File: LICENSE.txt
